mbed_build/__init__.py
mbed_build/__main__.py
mbed_build/_version.py
mbed_build/exceptions.py
mbed_build/mbed_tools.py
mbed_build/_internal/__init__.py
mbed_build/_internal/cmake_file.py
mbed_build/_internal/find_files.py
mbed_build/_internal/write_files.py
mbed_build/_internal/config/__init__.py
mbed_build/_internal/config/assemble_build_config.py
mbed_build/_internal/config/bootloader_overrides.py
mbed_build/_internal/config/config.py
mbed_build/_internal/config/cumulative_data.py
mbed_build/_internal/config/source.py
mbed_build/_internal/mbed_tools/__init__.py
mbed_build/_internal/mbed_tools/configure.py
mbed_build/_internal/templates/__init__.py
mbed_build/_internal/templates/mbed_config.tmpl
mbed_build-1.2.4.dist-info/LICENSE
mbed_build-1.2.4.dist-info/METADATA
mbed_build-1.2.4.dist-info/WHEEL
mbed_build-1.2.4.dist-info/top_level.txt
mbed_build-1.2.4.dist-info/RECORD
