Metadata-Version: 2.1
Name: mbed-build
Version: 1.2.4
Summary: Core Build Tools for Mbed OS
Home-page: https://github.com/ARMmbed/mbed-build
Author: Mbed team
Author-email: support@mbed.com
License: Apache 2.0
Keywords: Arm Mbed OS MbedOS build compile link cmake
Platform: UNKNOWN
Classifier: Development Status :: 3 - Alpha
Classifier: Intended Audience :: Developers
Classifier: License :: OSI Approved :: Apache Software License
Classifier: Programming Language :: Python
Classifier: Programming Language :: Python :: 3 :: Only
Classifier: Programming Language :: Python :: 3.6
Classifier: Programming Language :: Python :: 3.7
Classifier: Programming Language :: Python :: 3.8
Classifier: Topic :: Software Development :: Build Tools
Classifier: Topic :: Software Development :: Embedded Systems
Requires-Python: >=3.6,<4
Requires-Dist: python-dotenv
Requires-Dist: Click (==7.0)
Requires-Dist: Jinja2
Requires-Dist: mbed-project (~=2.0)
Requires-Dist: mbed-targets (~=1.1)
Requires-Dist: mbed-tools-lib (~=1.2)
Requires-Dist: tabulate
